pygosym/__init__.py
pygosym/pclntab.py
pygosym/symtab.py
pygosym-1.0.dist-info/LICENSE
pygosym-1.0.dist-info/WHEEL
pygosym-1.0.dist-info/METADATA
pygosym-1.0.dist-info/RECORD
